README.md
setup.cfg
setup.py
ibnsession/__init__.py
ibnsession.egg-info/PKG-INFO
ibnsession.egg-info/SOURCES.txt
ibnsession.egg-info/dependency_links.txt
ibnsession.egg-info/requires.txt
ibnsession.egg-info/top_level.txt
ibnsession/core/__init__.py
ibnsession/core/cisco.py
ibnsession/core/hs.py
ibnsession/core/huawei.py
ibnsession/core/linux.py
ibnsession/core/srx.py
ibnsession/tool/__init__.py
ibnsession/tool/ip.py