Metadata-Version: 2.1
Name: ibnsession
Version: 1.5.1
Summary: Library for IBN
Home-page: UNKNOWN
Author: ZF
Author-email: zofon@qq.com
License: UNKNOWN
Keywords: ibn,ops
Platform: windows or Linux
Classifier: Development Status :: 5 - Production/Stable
Classifier: Intended Audience :: Developers
Classifier: Programming Language :: Python :: 3.6
Classifier: Operating System :: OS Independent
Classifier: Topic :: Software Development :: Libraries :: Python Modules
Requires-Python: >=3.6.0
